deployit/__init__.py
deployit/providers/__init__.py
deployit/providers/jenkins/__init__.py
deployit/providers/jenkins/client.py
deployit/providers/jenkins/clients/__init__.py
deployit/providers/jenkins/clients/http.py
deployit/providers/jenkins/clients/jenkins.py
deployit/providers/jenkins/endpoints/__init__.py
deployit/providers/jenkins/endpoints/build.py
deployit/providers/jenkins/endpoints/common.py
deployit/providers/jenkins/endpoints/job.py
deployit/providers/jenkins/endpoints/queue.py
deployit/providers/jenkins/models/__init__.py
deployit/providers/jenkins/models/base.py
deployit/providers/jenkins/models/build.py
deployit/providers/jenkins/models/build_stage.py
deployit/providers/jenkins/models/job.py
deployit/providers/jenkins/models/queue.py
deployit/providers/jenkins/models/url.py
deployit/providers/jenkins/parameters/__init__.py
deployit/providers/jenkins/parameters/base.py
deployit/providers/jenkins/presentation/__init__.py
deployit/providers/jenkins/presentation/config.py
deployit/providers/jenkins/presentation/rich.py
deployit/providers/jenkins/services/__init__.py
deployit/providers/jenkins/services/base.py
deployit/providers/jenkins/services/build.py
deployit/providers/jenkins/services/build_stage.py
deployit/providers/jenkins/services/common.py
deployit/providers/jenkins/services/job.py
deployit/providers/jenkins/services/queue.py
deployit/providers/jenkins/services/utils_job.py
deployit/providers/jenkins/utils/__init__.py
deployit/providers/jenkins/utils/config.py
deployit/providers/jenkins/utils/decorators.py
deployit/providers/jenkins/utils/errors.py
deployit/providers/jenkins/utils/filter.py
deployit/providers/jenkins/utils/time.py
tests/__init__.py
tests/providers/__init__.py
tests/providers/jenkins/__init__.py
tests/providers/jenkins/clients/__init__.py
tests/providers/jenkins/clients/test_http.py
tests/providers/jenkins/clients/test_jenkins.py
tests/providers/jenkins/models/__init__.py
tests/providers/jenkins/models/test_base.py
deployit_sdk-0.1.2.dist-info/LICENSE
deployit_sdk-0.1.2.dist-info/METADATA
deployit_sdk-0.1.2.dist-info/WHEEL
deployit_sdk-0.1.2.dist-info/top_level.txt
deployit_sdk-0.1.2.dist-info/RECORD
