Metadata-Version: 2.1
Name: deployit-sdk
Version: 0.1.2
Home-page: https://github.com/victor-mariano-leite/deployit
Author: Victor Mariano Leite
Author-email: marianoleite44@gmail.com
License-File: LICENSE
Requires-Dist: rich >=12
Requires-Dist: pydantic
Requires-Dist: requests
